sosbackups/__init__.py
sosbackups/classes/__init__.py
sosbackups/classes/rsyncplug.py
sosbackups/modules/__init__.py
sosbackups/plugins/__init__.py
sosbackups/plugins/sbcopy.py
sosbackups/plugins/sbcronsync.py
sosbackups/plugins/sbpush.py
sosbackups/plugins/sbretention.py
sosbackups-0.0.100.data/data/share/sosbackups/etc/sosbackups/exclude.lst
sosbackups-0.0.100.data/data/share/sosbackups/etc/sosbackups/rc.default
sosbackups-0.0.100.data/data/share/sosbackups/etc/sosbackups/sosbackups.yml.example
sosbackups-0.0.100.data/data/share/sosbackups/init.d/sosbackups.sh
sosbackups-0.0.100.data/data/share/sosbackups/logrotate.d/sosbackups
sosbackups-0.0.100.data/scripts/sosbackups
sosbackups-0.0.100.dist-info/LICENSE.txt
sosbackups-0.0.100.dist-info/METADATA
sosbackups-0.0.100.dist-info/WHEEL
sosbackups-0.0.100.dist-info/top_level.txt
sosbackups-0.0.100.dist-info/RECORD
