Metadata-Version: 2.1
Name: sosbackups
Version: 0.0.100
Summary: sosbackups
Home-page: https://github.com/decryptus/sosbackups
Author: Adrien Delle Cave
Author-email: pypi@doowan.net
License: License GPL-2
Platform: UNKNOWN
Requires-Dist: croniter
Requires-Dist: dwho (>=0.3.56)
Requires-Dist: httpdis (>=0.6.22)
Requires-Dist: shellescape
Requires-Dist: sonicprobe (>=0.3.45)
Requires-Dist: subprocess32
